{
  "title": "林泽琪的小学成长纪念册",
  "author": "沈万三",
  "company": "OpenClaw",
  "subject": "林泽琪｜环翠园小学｜Expert Designer重新设计版",
  "lang": "zh-CN",
  "layout": "LAYOUT_WIDE",
  "theme": {
    "bg": "FEFAE0",
    "title": "283618",
    "text": "606C38",
    "accent": "DDA15E",
    "muted": "A3B18A"
  },
  "expertDesigner": {
    "mode": true,
    "preset": "教育温暖风",
    "redesignLevel": "high",
    "designDirection": "森林手账感 + 童年纪念册 + 杂志化编排",
    "notes": [
      "不再沿用昨天那种常规图文页",
      "整体改为更强的杂志感、手账感、版式节奏感",
      "目录页改为章节卡片导航",
      "年级页加入标签、引语、关键词模块",
      "成长关键词页改为四卡片拼贴布局",
      "毕业页改为大留白情绪收尾页"
    ]
  },
  "slides": [
    {
      "type": "cover-redesign",
      "title": "林泽琪",
      "subtitle": "小学成长纪念册",
      "meta": "环翠园小学 · 一年级到六年级",
      "quote": "把六年的风、光、脚步和笑声，装订成一本温柔发亮的童年纪念册。",
      "imagePath": "linzeqi-totoro-cover.png",
      "designHint": "封面做成杂志封面感：超大标题、竖向副标、右侧主视觉、底部一行时间信息。"
    },
    {
      "type": "toc-cards",
      "title": "成长章节",
      "subtitle": "六年像六张慢慢展开的书页",
      "sections": [
        "01 初入校园",
        "02 养成习惯",
        "03 兴趣发芽",
        "04 持续进步",
        "05 学会合作",
        "06 奔赴下一站"
      ],
      "body": "目录页不再是列表，而是章节导航页，要有卡片感、编号感和节奏感。",
      "designHint": "做成 2×3 章节卡片矩阵，每张卡片有编号、短标题、轻微错位和纸片感。"
    },
    {
      "type": "grade-hero",
      "title": "一年级｜初入校园",
      "subtitle": "第一次走进校园，连风都像在轻声欢迎",
      "tag": "关键词：适应 / 勇敢 / 开始",
      "bullets": [
        "背上小书包，第一次迈进小学大门",
        "认识老师和同学，慢慢融入班级",
        "学会整理书本和文具",
        "从害羞紧张到愿意开口表达"
      ],
      "quote": "每一个第一次，都是成长悄悄开始的地方。",
      "imagePath": "child-growth-grade1.png",
      "designHint": "左文右图，但文字区加入手账标签、短引语和浅色便签块。"
    },
    {
      "type": "grade-hero",
      "title": "二年级｜开始独立，养成习惯",
      "subtitle": "在安静又重复的日常里，慢慢长出稳定的力量",
      "tag": "关键词：规律 / 自律 / 稳定",
      "bullets": [
        "作息更规律，学习更主动",
        "阅读和书写习惯逐渐形成",
        "做事开始有自己的节奏",
        "与同学相处更自然、更融洽"
      ],
      "quote": "真正的成长，很多时候发生在看起来平静的日常里。",
      "imagePath": "linzeqi-totoro-grade2.png",
      "designHint": "加入顶部细标签和底部短引语，让页面不只是图文对半。"
    },
    {
      "type": "grade-hero",
      "title": "三年级｜找到兴趣，敢于表达",
      "subtitle": "当热爱发芽，自信也会悄悄长出来",
      "tag": "关键词：兴趣 / 表达 / 自信",
      "bullets": [
        "开始找到自己喜欢的事情",
        "愿意举手发言，表达想法",
        "参加活动，尝试展示自己",
        "在鼓励中越来越相信自己"
      ],
      "quote": "当热爱有了名字，眼睛也会跟着亮起来。",
      "imagePath": "child-growth-grade3.png",
      "designHint": "这页要更轻盈，排版更活一点，体现兴趣发芽的感觉。"
    },
    {
      "type": "grade-collage",
      "title": "四年级｜全面发展，持续进步",
      "subtitle": "不只是成绩在变好，眼里的光也越来越亮",
      "tag": "关键词：进步 / 坚持 / 丰富",
      "bullets": [
        "学习能力更稳，状态更均衡",
        "开始学会规划、总结和调整",
        "参与更多校园活动与实践",
        "面对困难时更有耐心与韧性"
      ],
      "quote": "这一年，成长不再只是一条线，而像一整片慢慢展开的风景。",
      "designHint": "无图页重做成拼贴式成长页：左侧大标题，右侧四宫格卡片/证书占位/活动占位，做出层次。"
    },
    {
      "type": "grade-hero",
      "title": "五年级｜承担责任，学会合作",
      "subtitle": "从做好自己，到懂得和大家一起把事情做好",
      "tag": "关键词：责任 / 合作 / 担当",
      "bullets": [
        "在班级中承担更多责任",
        "合作意识和表达能力更强",
        "做事更有条理，也更有担当",
        "懂得帮助同学、照顾集体"
      ],
      "quote": "真正的长大，是开始懂得和大家一起把事情做好。",
      "imagePath": "linzeqi-totoro-grade5.png",
      "designHint": "加一块小模块强调‘我在集体中的角色’，不要只剩说明文。"
    },
    {
      "type": "grade-hero",
      "title": "六年级｜自信成长，奔赴下一站",
      "subtitle": "告别童年的一段路，也准备迎接更大的世界",
      "tag": "关键词：毕业 / 感谢 / 未来",
      "bullets": [
        "回看六年，收获了勇敢与自信",
        "更加沉稳，也更懂珍惜陪伴",
        "感谢老师、同学和校园时光",
        "带着期待走向新的旅程"
      ],
      "quote": "再见不是结束，而是带着这段光亮，走向更远的地方。",
      "imagePath": "child-growth-grade6.png",
      "designHint": "收束感更强，图片和文字不要平均分，要更偏情绪页。"
    },
    {
      "type": "keywords-collage",
      "title": "成长关键词",
      "subtitle": "六年时间，把这些词一点一点写进了林泽琪的身上",
      "keywords": [
        "勇敢｜从害羞到敢表达",
        "自律｜从提醒到主动完成",
        "热爱｜从尝试到真正喜欢",
        "担当｜从独立到学会合作"
      ],
      "body": "这一页不再做列表，而是做成四张圆角卡片 + 手写标签式标题的拼贴布局。",
      "designHint": "四张关键词卡片要有高低错落、轻微错位、纸片感和留白感。"
    },
    {
      "type": "ending-quote",
      "title": "毕业寄语",
      "subtitle": "愿你像林间的风一样自由，也像阳光一样坚定",
      "quote": "愿你永远保持好奇和善良，愿你带着笑容，走向更远的地方。",
      "body": "这页要像整本纪念册轻轻合上时留下的最后一句话。少一点信息，多一点余味。",
      "imagePath": "linzeqi-totoro-cover.png",
      "designHint": "做成大留白收尾页：左上标题，中央主寄语，右下角图片或淡化背景图。"
    }
  ]
}
